README.rst
setup.cfg
setup.py
click_extensions/__init__.py
click_extensions/commands.py
click_extensions/decorators.py
click_extensions/exit_codes.py
click_extensions/private_dir.py
click_extensions/utils.py
click_extensions.egg-info/PKG-INFO
click_extensions.egg-info/SOURCES.txt
click_extensions.egg-info/dependency_links.txt
click_extensions.egg-info/requires.txt
click_extensions.egg-info/top_level.txt