Metadata-Version: 1.0
Name: click-extensions
Version: 1.1.0
Summary: A set of utilities for Click
Home-page: https://github.com/naphatkrit/click-extensions
Author: Naphat Sanguansin
Author-email: naphat.krit@gmail.com
License: UNKNOWN
Keywords: click,extensions
Platform: UNKNOWN
